{
  "output_dir": "stake_thumbnails",
  "temp_dir": "temp_html",
  "metadata_dir": "metadata",
  "checkpoints_dir": "checkpoints",
  "js_fetcher_dir": ".",
  "webp_quality": 85,
  "webp_method": 6,
  "max_concurrent_requests": 3,
  "max_concurrent_downloads": 5,
  "max_concurrent_graphql": 2,
  "retry_attempts": 5,
  "retry_delay": 2,
  "request_delay": 1,
  "organize_by_provider": true,
  "generate_csv": true,
  "generate_json": true,
  "min_image_size": 100,
  "max_image_size": 1024,
  "allowed_image_formats": ["jpg", "jpeg", "png", "webp"],
  "user_agent": "Mozilla/5.0 (Windows NT 10.0; Win64; x64) AppleWebKit/537.36 (KHTML, like Gecko) Chrome/120.0.0.0 Safari/537.36",
  "games_per_request": 39,
  "enable_checkpoints": true,
  "auto_resume": true
}
