{
  "timestamp": "2025-08-06T22:59:54.246Z",
  "provider_slug": "belatra",
  "provider_name": "Belatra",
  "total_games": 76,
  "games_fetched": 76,
  "games": [
    {
      "game_id": "belatra-voodoo-coins",
      "title": "Voodoo Coins",
      "slug": "belatra-voodoo-coins",
      "provider": "Belatra",
      "thumbnail_url": "https://mediumrare.imgix.net/32fca9583ed8729df140f6ac9b628d8acb0a1774e8599ff66fa8c4fced41171d",
      "expected_filename": "Belatra - Voodoo Coins.webp",
      "game_url": "https://stake.com/casino/games/belatra-voodoo-coins",
      "extracted_at": "2025-08-07T02:20:11.790501"
    },
    {
      "game_id": "belatra-mummyland-treasures",
      "title": "Mummyland Treasures",
      "slug": "belatra-mummyland-treasures",
      "provider": "Belatra",
      "thumbnail_url": "https://mediumrare.imgix.net/8eaca5e38c4a97639df47bcb5bcf9794c9f2ffde66296317988d974606e8f2a0",
      "expected_filename": "Belatra - Mummyland Treasures.webp",
      "game_url": "https://stake.com/casino/games/belatra-mummyland-treasures",
      "extracted_at": "2025-08-07T02:20:11.790501"
    },
    {
      "game_id": "belatra-santa-mummy",
      "title": "Santa Mummy",
      "slug": "belatra-santa-mummy",
      "provider": "Belatra",
      "thumbnail_url": "https://mediumrare.imgix.net/afcb899da300dfa90556564b2690dca55e06b465d3f1195fd7be4b5e19f81369",
      "expected_filename": "Belatra - Santa Mummy.webp",
      "game_url": "https://stake.com/casino/games/belatra-santa-mummy",
      "extracted_at": "2025-08-07T02:20:11.790501"
    },
    {
      "game_id": "belatra-cyber-gypsies",
      "title": "Cyber Gypsies",
      "slug": "belatra-cyber-gypsies",
      "provider": "Belatra",
      "thumbnail_url": "https://mediumrare.imgix.net/0af1b02c7d45c82a2c4db480c27f4b746332bbcba00f6cb2bfe5dda7c78245eb",
      "expected_filename": "Belatra - Cyber Gypsies.webp",
      "game_url": "https://stake.com/casino/games/belatra-cyber-gypsies",
      "extracted_at": "2025-08-07T02:20:11.790501"
    },
    {
      "game_id": "belatra-blast-the-bass",
      "title": "Blast the Bass",
      "slug": "belatra-blast-the-bass",
      "provider": "Belatra",
      "thumbnail_url": "https://mediumrare.imgix.net/a11ba3e3231128c36ba363809d2f4c63ebc6eeac2c6bdfb192668845e44d1386",
      "expected_filename": "Belatra - Blast the Bass.webp",
      "game_url": "https://stake.com/casino/games/belatra-blast-the-bass",
      "extracted_at": "2025-08-07T02:20:11.790501"
    },
    {
      "game_id": "belatra-bears-tricks",
      "title": "Bear's Tricks",
      "slug": "belatra-bears-tricks",
      "provider": "Belatra",
      "thumbnail_url": "https://mediumrare.imgix.net/b998bf9e7dc8268398b5a7a46e44c4dc5e16ebf5f2af146040db624d2396de23",
      "expected_filename": "Belatra - Bear's Tricks.webp",
      "game_url": "https://stake.com/casino/games/belatra-bears-tricks",
      "extracted_at": "2025-08-07T02:20:11.790501"
    },
    {
      "game_id": "belatra-dragons-bonanza",
      "title": "Dragon's Bonanza",
      "slug": "belatra-dragons-bonanza",
      "provider": "Belatra",
      "thumbnail_url": "https://mediumrare.imgix.net/133363e49fe2e9e3e52336bee03df4683bb16423a9b412cfc572e1fd7354ae88",
      "expected_filename": "Belatra - Dragon's Bonanza.webp",
      "game_url": "https://stake.com/casino/games/belatra-dragons-bonanza",
      "extracted_at": "2025-08-07T02:20:11.790501"
    },
    {
      "game_id": "belatra-big-bang",
      "title": "Big Bang",
      "slug": "belatra-big-bang",
      "provider": "Belatra",
      "thumbnail_url": "https://mediumrare.imgix.net/9e2739f354db3643551c61f8bad15de507430666bdb32ad16cf8e72067ba979a",
      "expected_filename": "Belatra - Big Bang.webp",
      "game_url": "https://stake.com/casino/games/belatra-big-bang",
      "extracted_at": "2025-08-07T02:20:11.790501"
    },
    {
      "game_id": "belatra-rise-of-zeus",
      "title": "Rise of Zeus",
      "slug": "belatra-rise-of-zeus",
      "provider": "Belatra",
      "thumbnail_url": "https://mediumrare.imgix.net/cbc338b600834f94983f090e2b5ad83db1a85596d033034c4b9d1e2915a7dafc",
      "expected_filename": "Belatra - Rise of Zeus.webp",
      "game_url": "https://stake.com/casino/games/belatra-rise-of-zeus",
      "extracted_at": "2025-08-07T02:20:11.790501"
    },
    {
      "game_id": "belatra-big-wild-buffalo",
      "title": "Big Wild Buffalo",
      "slug": "belatra-big-wild-buffalo",
      "provider": "Belatra",
      "thumbnail_url": "https://mediumrare.imgix.net/1ae4cecef19dc7ebab5b1ae70dbb1e8aa13554079c17d7a77afd6811ed3709a9",
      "expected_filename": "Belatra - Big Wild Buffalo.webp",
      "game_url": "https://stake.com/casino/games/belatra-big-wild-buffalo",
      "extracted_at": "2025-08-07T02:20:11.790501"
    },
    {
      "game_id": "belatra-buy-bonus-of-maya",
      "title": "#buyBonus of Maya",
      "slug": "belatra-buy-bonus-of-maya",
      "provider": "Belatra",
      "thumbnail_url": "https://mediumrare.imgix.net/ce0abad86bbcde62b385f8f650d98e11071e68bbe3d86bdcfae342c2a410b6c0",
      "expected_filename": "Belatra - #buyBonus of Maya.webp",
      "game_url": "https://stake.com/casino/games/belatra-buy-bonus-of-maya",
      "extracted_at": "2025-08-07T02:20:11.790501"
    },
    {
      "game_id": "belatra-princess-suki",
      "title": "Princess Suki",
      "slug": "belatra-princess-suki",
      "provider": "Belatra",
      "thumbnail_url": "https://mediumrare.imgix.net/d48bb07dadd23a99e00e222e1fc056070fb4e7e0ceae1f5e2a70ec3e2e5867c5",
      "expected_filename": "Belatra - Princess Suki.webp",
      "game_url": "https://stake.com/casino/games/belatra-princess-suki",
      "extracted_at": "2025-08-07T02:20:11.790501"
    },
    {
      "game_id": "belatra-cleos-book",
      "title": "Cleo’s Book",
      "slug": "belatra-cleos-book",
      "provider": "Belatra",
      "thumbnail_url": "https://mediumrare.imgix.net/abd35385262d3db6bf218a383d575cfeaf56d85afd5e01578d9eb68af103f261",
      "expected_filename": "Belatra - Cleo’s Book.webp",
      "game_url": "https://stake.com/casino/games/belatra-cleos-book",
      "extracted_at": "2025-08-07T02:20:11.790501"
    },
    {
      "game_id": "belatra-richy-hog",
      "title": "Richy Hog",
      "slug": "belatra-richy-hog",
      "provider": "Belatra",
      "thumbnail_url": "https://mediumrare.imgix.net/6d59d97d694575e82c50da8a523c4773a5bf161d98d43e304e2c65b67b3b7a4a",
      "expected_filename": "Belatra - Richy Hog.webp",
      "game_url": "https://stake.com/casino/games/belatra-richy-hog",
      "extracted_at": "2025-08-07T02:20:11.790501"
    },
    {
      "game_id": "belatra-lucies-cats",
      "title": "Lucie's Cats",
      "slug": "belatra-lucies-cats",
      "provider": "Belatra",
      "thumbnail_url": "https://mediumrare.imgix.net/a7d5f6da7ca188120cd350c1a81b317eb33379dfc97a409f789dc7378dfb6616",
      "expected_filename": "Belatra - Lucie's Cats.webp",
      "game_url": "https://stake.com/casino/games/belatra-lucies-cats",
      "extracted_at": "2025-08-07T02:20:11.790501"
    },
    {
      "game_id": "belatra-crystals-digger",
      "title": "Crystals Digger",
      "slug": "belatra-crystals-digger",
      "provider": "Belatra",
      "thumbnail_url": "https://mediumrare.imgix.net/f94696e29e2bf6e1011ff455cdc08c1a79bdd749de6bd58b3b164207c855484b",
      "expected_filename": "Belatra - Crystals Digger.webp",
      "game_url": "https://stake.com/casino/games/belatra-crystals-digger",
      "extracted_at": "2025-08-07T02:20:11.790501"
    },
    {
      "game_id": "belatra-xmas-buffalo",
      "title": "X-Mas Buffalo",
      "slug": "belatra-xmas-buffalo",
      "provider": "Belatra",
      "thumbnail_url": "https://mediumrare.imgix.net/ccda8f648f39053ab16a4170c102a60b7b94c7bc441c8fb7e4930696952b405c",
      "expected_filename": "Belatra - X-Mas Buffalo.webp",
      "game_url": "https://stake.com/casino/games/belatra-xmas-buffalo",
      "extracted_at": "2025-08-07T02:20:11.790501"
    },
    {
      "game_id": "belatra-zombie-town",
      "title": "Zombie Town",
      "slug": "belatra-zombie-town",
      "provider": "Belatra",
      "thumbnail_url": "https://mediumrare.imgix.net/39e1b5cbbe9326fe8c93869b540823e2be10f063a0dd267286951be0678f5af6",
      "expected_filename": "Belatra - Zombie Town.webp",
      "game_url": "https://stake.com/casino/games/belatra-zombie-town",
      "extracted_at": "2025-08-07T02:20:11.790501"
    },
    {
      "game_id": "belatra-wild-fruit-jam",
      "title": "Wild Fruit Jam",
      "slug": "belatra-wild-fruit-jam",
      "provider": "Belatra",
      "thumbnail_url": "https://mediumrare.imgix.net/ba50215560efa0628333139ab5bde19dd90d0759647fba19bfc53db511937890",
      "expected_filename": "Belatra - Wild Fruit Jam.webp",
      "game_url": "https://stake.com/casino/games/belatra-wild-fruit-jam",
      "extracted_at": "2025-08-07T02:20:11.790501"
    },
    {
      "game_id": "belatra-piggy-bank",
      "title": "Piggy Bank",
      "slug": "belatra-piggy-bank",
      "provider": "Belatra",
      "thumbnail_url": "https://mediumrare.imgix.net/99cb6549ec80a977d4dc2d9f4daf6c1adc7799e86920b94601a590f6687fd273",
      "expected_filename": "Belatra - Piggy Bank.webp",
      "game_url": "https://stake.com/casino/games/belatra-piggy-bank",
      "extracted_at": "2025-08-07T02:20:11.790501"
    },
    {
      "game_id": "belatra-j-monsters",
      "title": "J.Monsters",
      "slug": "belatra-j-monsters",
      "provider": "Belatra",
      "thumbnail_url": "https://mediumrare.imgix.net/01af679de92839f4e6134ea4ebc2bb1c50748c406f0ae8899c013c0873096e9e",
      "expected_filename": "Belatra - J.Monsters.webp",
      "game_url": "https://stake.com/casino/games/belatra-j-monsters",
      "extracted_at": "2025-08-07T02:20:11.790501"
    },
    {
      "game_id": "belatra-legacy-of-doom",
      "title": "Legacy of Doom",
      "slug": "belatra-legacy-of-doom",
      "provider": "Belatra",
      "thumbnail_url": "https://mediumrare.imgix.net/0e37c27e44e746794a832b0785b71d25b617d0aef77c84cda7a85e88e641fee2",
      "expected_filename": "Belatra - Legacy of Doom.webp",
      "game_url": "https://stake.com/casino/games/belatra-legacy-of-doom",
      "extracted_at": "2025-08-07T02:20:11.790501"
    },
    {
      "game_id": "belatra-africa-gold-ii",
      "title": "Africa Gold II",
      "slug": "belatra-africa-gold-ii",
      "provider": "Belatra",
      "thumbnail_url": "https://mediumrare.imgix.net/58b971f485182b1f3b6e3aa800c8526688d9db4ad069f289bafbaa9c25298c54",
      "expected_filename": "Belatra - Africa Gold II.webp",
      "game_url": "https://stake.com/casino/games/belatra-africa-gold-ii",
      "extracted_at": "2025-08-07T02:20:11.790501"
    },
    {
      "game_id": "belatra-tortuga-codex",
      "title": "Tortuga Codex",
      "slug": "belatra-tortuga-codex",
      "provider": "Belatra",
      "thumbnail_url": "https://mediumrare.imgix.net/a762df2c3f0244463abfbc01a6d5d1daba75f3e7e9a9e0eb1fa0da2850abbabc",
      "expected_filename": "Belatra - Tortuga Codex.webp",
      "game_url": "https://stake.com/casino/games/belatra-tortuga-codex",
      "extracted_at": "2025-08-07T02:20:11.790501"
    },
    {
      "game_id": "belatra-super-sevens",
      "title": "Super Sevens",
      "slug": "belatra-super-sevens",
      "provider": "Belatra",
      "thumbnail_url": "https://mediumrare.imgix.net/02071d611315d1d6428d6ded0203ac2b6ce5aa9e5b3b8929b46166a43442d153",
      "expected_filename": "Belatra - Super Sevens.webp",
      "game_url": "https://stake.com/casino/games/belatra-super-sevens",
      "extracted_at": "2025-08-07T02:20:11.790501"
    },
    {
      "game_id": "belatra-the-night-racing",
      "title": "The Night Racing",
      "slug": "belatra-the-night-racing",
      "provider": "Belatra",
      "thumbnail_url": "https://mediumrare.imgix.net/5a9ada090af145106c145b058a736ce4563b06944255497134f8ecb53a0822fd",
      "expected_filename": "Belatra - The Night Racing.webp",
      "game_url": "https://stake.com/casino/games/belatra-the-night-racing",
      "extracted_at": "2025-08-07T02:20:11.790501"
    },
    {
      "game_id": "belatra-88-dragons-treasure",
      "title": "88 Dragons Treasure",
      "slug": "belatra-88-dragons-treasure",
      "provider": "Belatra",
      "thumbnail_url": "https://mediumrare.imgix.net/c5c5ccc2c9914c6be401e786586b33aebb8e34634a78c72083c5183ffb68f0e0",
      "expected_filename": "Belatra - 88 Dragons Treasure.webp",
      "game_url": "https://stake.com/casino/games/belatra-88-dragons-treasure",
      "extracted_at": "2025-08-07T02:20:11.790501"
    },
    {
      "game_id": "belatra-mayan-book-multi-choice",
      "title": "Mayan Book Multi Choice",
      "slug": "belatra-mayan-book-multi-choice",
      "provider": "Belatra",
      "thumbnail_url": "https://mediumrare.imgix.net/5dc08dbe35aa88947ee6970e8d9167a914eee66f70d5802670e79b0218d235cb",
      "expected_filename": "Belatra - Mayan Book Multi Choice.webp",
      "game_url": "https://stake.com/casino/games/belatra-mayan-book-multi-choice",
      "extracted_at": "2025-08-07T02:20:11.790501"
    },
    {
      "game_id": "belatra-make-it-gold",
      "title": "Make it Gold",
      "slug": "belatra-make-it-gold",
      "provider": "Belatra",
      "thumbnail_url": "https://mediumrare.imgix.net/1455281698227aab814ebf035bf0988a379f74130efe8c9630297a26ae527983",
      "expected_filename": "Belatra - Make it Gold.webp",
      "game_url": "https://stake.com/casino/games/belatra-make-it-gold",
      "extracted_at": "2025-08-07T02:20:11.790501"
    },
    {
      "game_id": "belatra-chicagobangbang",
      "title": "Chicago, bang, bang!",
      "slug": "belatra-chicagobangbang",
      "provider": "Belatra",
      "thumbnail_url": "https://mediumrare.imgix.net/f8659db2beb669460ea09f2ae5b5de5f1368636d7e3ffe50db97c25da28d1e87",
      "expected_filename": "Belatra - Chicago, bang, bang!.webp",
      "game_url": "https://stake.com/casino/games/belatra-chicagobangbang",
      "extracted_at": "2025-08-07T02:20:11.790501"
    },
    {
      "game_id": "belatra-lavish-joker",
      "title": "Lavish Joker",
      "slug": "belatra-lavish-joker",
      "provider": "Belatra",
      "thumbnail_url": "https://mediumrare.imgix.net/9d1bd277d197ab87390537518e199b4f7ec2ed6b2c653ec68fa96999953bc468",
      "expected_filename": "Belatra - Lavish Joker.webp",
      "game_url": "https://stake.com/casino/games/belatra-lavish-joker",
      "extracted_at": "2025-08-07T02:20:11.790501"
    },
    {
      "game_id": "belatra-sevens",
      "title": "Sevens",
      "slug": "belatra-sevens",
      "provider": "Belatra",
      "thumbnail_url": "https://mediumrare.imgix.net/6700600c207859f95ca2dd602b6e7c2a59bf436cc02e58cae8fded31a43917be",
      "expected_filename": "Belatra - Sevens.webp",
      "game_url": "https://stake.com/casino/games/belatra-sevens",
      "extracted_at": "2025-08-07T02:20:11.790501"
    },
    {
      "game_id": "belatra-500-juicy-fruits",
      "title": "500 Juicy Fruits",
      "slug": "belatra-500-juicy-fruits",
      "provider": "Belatra",
      "thumbnail_url": "https://mediumrare.imgix.net/9faeea3879348a69e812f7c5e4b8ba58d8241c011b8fff3ee901e44f07747566",
      "expected_filename": "Belatra - 500 Juicy Fruits.webp",
      "game_url": "https://stake.com/casino/games/belatra-500-juicy-fruits",
      "extracted_at": "2025-08-07T02:20:11.790501"
    },
    {
      "game_id": "belatra-7-days-anotherland",
      "title": "7 Days Anotherland",
      "slug": "belatra-7-days-anotherland",
      "provider": "Belatra",
      "thumbnail_url": "https://mediumrare.imgix.net/731eeac9e6e1331cf78923e88da0429032be1e26b9ffd4aa4f55d72735a9b341",
      "expected_filename": "Belatra - 7 Days Anotherland.webp",
      "game_url": "https://stake.com/casino/games/belatra-7-days-anotherland",
      "extracted_at": "2025-08-07T02:20:11.790501"
    },
    {
      "game_id": "belatra-rockets",
      "title": "Rockets",
      "slug": "belatra-rockets",
      "provider": "Belatra",
      "thumbnail_url": "https://mediumrare.imgix.net/d6db73a66754b775b9a27ae72215fe506abd9b1f6a84cb052fed636818d02ddc",
      "expected_filename": "Belatra - Rockets.webp",
      "game_url": "https://stake.com/casino/games/belatra-rockets",
      "extracted_at": "2025-08-07T02:20:11.790501"
    },
    {
      "game_id": "belatra-xmas-gifts",
      "title": "Xmas Gifts",
      "slug": "belatra-xmas-gifts",
      "provider": "Belatra",
      "thumbnail_url": "https://mediumrare.imgix.net/b0c4e14712d5f7b73eb52ac4e994a952f014bb6bfc1f59c022fad7484b5b9d55",
      "expected_filename": "Belatra - Xmas Gifts.webp",
      "game_url": "https://stake.com/casino/games/belatra-xmas-gifts",
      "extracted_at": "2025-08-07T02:20:11.790501"
    },
    {
      "game_id": "belatra-full-moon-magic",
      "title": "Full Moon Magic",
      "slug": "belatra-full-moon-magic",
      "provider": "Belatra",
      "thumbnail_url": "https://mediumrare.imgix.net/d71e27212b3b0361716285e5cf3728820403c3545395c36178fdc1a4c9297481",
      "expected_filename": "Belatra - Full Moon Magic.webp",
      "game_url": "https://stake.com/casino/games/belatra-full-moon-magic",
      "extracted_at": "2025-08-07T02:20:11.790501"
    },
    {
      "game_id": "belatra-frog-creek",
      "title": "Frog Creek",
      "slug": "belatra-frog-creek",
      "provider": "Belatra",
      "thumbnail_url": "https://mediumrare.imgix.net/26dd47f0f86b3c0fb2ec9ceeccbf089aa953f0cef5b19977349420a3720eb937",
      "expected_filename": "Belatra - Frog Creek.webp",
      "game_url": "https://stake.com/casino/games/belatra-frog-creek",
      "extracted_at": "2025-08-07T02:20:11.790501"
    },
    {
      "game_id": "belatra-jewels",
      "title": "Jewels",
      "slug": "belatra-jewels",
      "provider": "Belatra",
      "thumbnail_url": "https://mediumrare.imgix.net/e8b13b3b74aeeeae59886407b88b63b624362c778d845d4f8f5ac624bb08a93e",
      "expected_filename": "Belatra - Jewels.webp",
      "game_url": "https://stake.com/casino/games/belatra-jewels",
      "extracted_at": "2025-08-07T02:20:11.790501"
    },
    {
      "id": "b3d19eae-1b1a-4c61-a46e-5df84559eed8",
      "name": "Golden Lemon",
      "slug": "belatra-golden-lemon",
      "thumbnailUrl": "https://mediumrare.imgix.net/a1b9c5a4bdd2e3053487ad4fba3475dfc50b859da5954e678930bc12567dad47",
      "thumbnailBlurHash": "elO_L5oLI5WEV#%8j?RZWDaka7azk7kAa%xxWDoZodawH,a|oxj[tI",
      "isBlocked": false,
      "isWidgetEnabled": true,
      "playerCount": 0,
      "groupGames": []
    },
    {
      "id": "37b906b1-5a52-4975-85f9-fb3669817a58",
      "name": "Halloween Crystals",
      "slug": "belatra-halloween-crystals",
      "thumbnailUrl": "https://mediumrare.imgix.net/61754cd093e510428585ae41fe0b710c1ca66c6d32c93af225ef2306c75862b6",
      "thumbnailBlurHash": "edMX.oSxMe9@e.0wj?RoJ6kVv3r@o}t7XQYPahjYkVRjvga~WANZof",
      "isBlocked": false,
      "isWidgetEnabled": true,
      "playerCount": 0,
      "groupGames": []
    },
    {
      "id": "74b9e432-f37a-4fb5-b639-907ab312ac5c",
      "name": "Seven Fruits",
      "slug": "belatra-seven-fruits",
      "thumbnailUrl": "https://mediumrare.imgix.net/27cfd778f37af6f372a151948e9584f52d9a0f4e3fc825cc780bb605f94924b3",
      "thumbnailBlurHash": "euJRu_S}EyS^M|hkj?ODjbR.O+sAn+oLShNOsWr?WoX3EwW;xZR+w|",
      "isBlocked": false,
      "isWidgetEnabled": true,
      "playerCount": 0,
      "groupGames": []
    },
    {
      "id": "a3963f45-62af-4557-bfa0-897945e3cc17",
      "name": "Book of Doom",
      "slug": "belatra-bookof-doom",
      "thumbnailUrl": "https://mediumrare.imgix.net/eae4dc8e029a37f35c4161a2e356bc380377cfdf683d6bdf388880cb6fa316d6",
      "thumbnailBlurHash": "eNP}xCR.,-xrRONBWE-Vt5t7s#WARkWEt7.ARk9aWEIV*ws:I[oJI]",
      "isBlocked": false,
      "isWidgetEnabled": true,
      "playerCount": 0,
      "groupGames": []
    },
    {
      "id": "45c99c97-da0f-4037-a69f-c1ce88dfa26f",
      "name": "Winter Thunder",
      "slug": "belatra-winter-thunder",
      "thumbnailUrl": "https://mediumrare.imgix.net/9b3c88a38d3fab7d39cc3b00b745a983cd609113ec2addf71603910a2701f100",
      "thumbnailBlurHash": "eiM8jOR*yExux]}+axxZt6xuK7ozRPRjoJ-noMR+RkNHEOaet6kCoe",
      "isBlocked": false,
      "isWidgetEnabled": true,
      "playerCount": 0,
      "groupGames": []
    },
    {
      "id": "733d920e-fc09-493d-9328-f0883f8d8957",
      "name": "Irish Thunder",
      "slug": "belatra-irish-thunder",
      "thumbnailUrl": "https://mediumrare.imgix.net/1af3d67b782f47a0d86b429ef7ad61b38bdde016c25229f59680c9a25e3512fe",
      "thumbnailBlurHash": "ekO:66w{lVSgs:Bqs9tne.ofSuadvgoeR*u4R*rWX8NFslS2kWa#Nt",
      "isBlocked": false,
      "isWidgetEnabled": true,
      "playerCount": 0,
      "groupGames": []
    },
    {
      "id": "7e878774-e2ce-4fa1-8f5f-1a9ad7e587c8",
      "name": "Catch & Snatch",
      "slug": "belatra-catch-snatch",
      "thumbnailUrl": "https://mediumrare.imgix.net/0defdb2c897bfb4ad41b35cc0d4486fb7f44a125afeeb45f3333888681d795a5",
      "thumbnailBlurHash": "eXHoFkxn0kwMwaOuX8OZr=$~2zNys;RioLy3oNe9WCRkM+nO#*o#kW",
      "isBlocked": false,
      "isWidgetEnabled": true,
      "playerCount": 0,
      "groupGames": []
    },
    {
      "id": "d38f241e-e48d-4694-8e38-814e124954cf",
      "name": "5 Wild Wild Peppers",
      "slug": "belatra-5-wild-wild-peppers",
      "thumbnailUrl": "https://mediumrare.imgix.net/c8172fb11278846eacdacefede3a28dc0b2a8ec287ef90aca22f077bf7c37642",
      "thumbnailBlurHash": "elMEIKe@I]WZI[Z?e?bvWFX9Itn%ska$s,G^skR*W?V]D.oHS%SiXA",
      "isBlocked": false,
      "isWidgetEnabled": true,
      "playerCount": 0,
      "groupGames": []
    },
    {
      "id": "a44cb195-26c2-4600-8b48-faacd04cb1ed",
      "name": "Master Of Gold",
      "slug": "belatra-master-of-gold",
      "thumbnailUrl": "https://mediumrare.imgix.net/65dc5c7bd106502b02f19e54e50a89c4d0b828dda76428b522747f5cc3f77c8b",
      "thumbnailBlurHash": "eTP=5Dx-h=9@#YQ6xvS7oMxuMRsEpc%2ScGVoatRNGRPVaW9W-RQkB",
      "isBlocked": false,
      "isWidgetEnabled": true,
      "playerCount": 0,
      "groupGames": []
    },
    {
      "id": "820d1582-76a7-4454-93c9-ecaf3e71f588",
      "name": "Triple X Hot Pepper",
      "slug": "belatra-triple-x-hot-pepper",
      "thumbnailUrl": "https://mediumrare.imgix.net/081bde5cd2ccb1480f64c592fb3bcfbd81e9470c5fe2389729ec63f7f4e4b508",
      "thumbnailBlurHash": "eRKLAiko7:kRO*#zS2PRoLpGL8M}wNnmjJG^RoVaRkVtBvnlS$X5xH",
      "isBlocked": false,
      "isWidgetEnabled": true,
      "playerCount": 0,
      "groupGames": []
    },
    {
      "id": "4d8920f4-27aa-433f-aa8d-9bc324a6c17c",
      "name": "7 Days The Spanish Armada",
      "slug": "belatra-7-days-the-spanish-armada",
      "thumbnailUrl": "https://mediumrare.imgix.net/40dc3b4c10fcd6645b4d34ba18a537c96f9ba3cb331e29ec433e2e2192c2e185",
      "thumbnailBlurHash": "ecJ+vDWBK8smS6?Qj[tRoIkBJ=W=s7ayn#XoWYM|bHae0joIkDj]oe",
      "isBlocked": false,
      "isWidgetEnabled": true,
      "playerCount": 0,
      "groupGames": []
    },
    {
      "id": "fcc3e406-cc47-48f4-9861-ce5ea239b09d",
      "name": "Hot Wild Pepper",
      "slug": "belatra-hot-wild-pepper",
      "thumbnailUrl": "https://mediumrare.imgix.net/f55db0ac1713ad7376728dced836a119438d3c9e04acafcbf40fa06cfd4ee40b",
      "thumbnailBlurHash": "eYQY;]so#QNd#RqIsBo#R+t7=Wt3oMf%S#PWSgrXX7RiiIS4XTS2bv",
      "isBlocked": false,
      "isWidgetEnabled": true,
      "playerCount": 0,
      "groupGames": []
    },
    {
      "id": "4e07fbfe-55e6-448b-8b47-a43555fc0b1b",
      "name": "Witch School",
      "slug": "belatra-witch-school",
      "thumbnailUrl": "https://mediumrare.imgix.net/4961ba1a03c39a688e1b3a17c2780960ed87e5c7ec471a4051d74ee5549d86cd",
      "thumbnailBlurHash": "elH-aEouD*WHRRI7W+obajs:9JWT%Jogoy-.fAahs;RlRVjcV|f7oc",
      "isBlocked": false,
      "isWidgetEnabled": true,
      "playerCount": 0,
      "groupGames": []
    },
    {
      "id": "e8fe2290-4a5e-4c5b-b958-83ca2ec0f176",
      "name": "An Escape from Alcatraz",
      "slug": "belatra-an-escape-from-alcatraz",
      "thumbnailUrl": "https://mediumrare.imgix.net/5e3c60409faf08ba0db21e6f3265aa4877bb6a48b6dc70990ee0ae25bafe3bf1",
      "thumbnailBlurHash": "egJ01wtRC9Z~XTtuT0TKrqsl2yR-wtsnnNkor=rqX8WDN3r=aKShf+",
      "isBlocked": false,
      "isWidgetEnabled": true,
      "playerCount": 0,
      "groupGames": []
    },
    {
      "id": "4508ed14-30ad-4464-9812-fbf8ed81e8e3",
      "name": "3x Super Peppers",
      "slug": "belatra-3x-super-peppers",
      "thumbnailUrl": "https://mediumrare.imgix.net/3cf8599060e40c455232446d2a1e69f45068d8537dd124631264a9892d990562",
      "thumbnailBlurHash": "ehFuP#P4B}#WJPrTTFTbrtb]GRbartjsbtqDnQq{WYRQ3drt#rR-w5",
      "isBlocked": false,
      "isWidgetEnabled": true,
      "playerCount": 0,
      "groupGames": []
    },
    {
      "id": "f0e6ea2a-11a9-493b-939a-fb2468327cef",
      "name": "Ancient Temple Gems",
      "slug": "belatra-ancient-temple-gems",
      "thumbnailUrl": "https://mediumrare.imgix.net/dea3b76f7561d0df38b209c92043f8c4e4296c6f9dde18d5afa8e47878cc2ad1",
      "thumbnailBlurHash": "eYCtxNkD6CWCwHVnaepdWBn#I}V@s,aetP%Ka#R4j]X5EPbI$_ogWA",
      "isBlocked": false,
      "isWidgetEnabled": true,
      "playerCount": 0,
      "groupGames": []
    },
    {
      "id": "b1c57825-1ed9-49ba-b843-5a0bc62b425e",
      "name": "Beauty and the Beast",
      "slug": "belatra-beauty-beast",
      "thumbnailUrl": "https://mediumrare.imgix.net/f2f3e70c1a10bc1db120eb3136f9bf0255af2f910b2812b8e60ead0bc655839d",
      "thumbnailBlurHash": "eZDd*2jeE+r=NGHsWZXToIoeO]kEnhaxoI?dt8VrWBRi5UbJxWays+",
      "isBlocked": false,
      "isWidgetEnabled": true,
      "playerCount": 0,
      "groupGames": []
    },
    {
      "id": "9b090ddf-5005-48bf-8e10-df05fedb487a",
      "name": "New York",
      "slug": "belatra-buybonus-new-york",
      "thumbnailUrl": "https://mediumrare.imgix.net/380a2a91ee03b144c04f99325bf3fbe35948b8c2cf78ce9925010ff0fe8b6d40",
      "thumbnailBlurHash": "eaI4#.$$D[otIaeTs:RrWSoh9CR-ohf2xttkRooct3aw9dakxVogot",
      "isBlocked": false,
      "isWidgetEnabled": true,
      "playerCount": 0,
      "groupGames": []
    },
    {
      "id": "092cc90a-c642-40c0-a818-9f994e589b64",
      "name": "Cafe Pin-Up",
      "slug": "belatra-cafe-pin-up",
      "thumbnailUrl": "https://mediumrare.imgix.net/f665e94bc568c80a6fc00c803b8a139dcd9fef3b66f3d8a70e9e0795e268f7e3",
      "thumbnailBlurHash": "eVIs2C%$GYtRV@zrx^%zt7wd3Srs%2s,jF-r#8RPsTIpR|wfxaahn,",
      "isBlocked": false,
      "isWidgetEnabled": true,
      "playerCount": 0,
      "groupGames": []
    },
    {
      "id": "039924fb-9149-4773-b7a3-1f869076dabb",
      "name": "Halloween",
      "slug": "belatra-halloween",
      "thumbnailUrl": "https://mediumrare.imgix.net/24bac1f2f65763e63cda04e76e456e1edaf29eae30686a3e408ef71a02535864",
      "thumbnailBlurHash": "eeMzzbR+#Tofwc0fbHwyn%j[+coLbZayNw?IjZocj[WVQ,oLShafs:",
      "isBlocked": false,
      "isWidgetEnabled": true,
      "playerCount": 0,
      "groupGames": []
    },
    {
      "id": "0ac508fc-7d5b-4812-a7a1-652ae0cb5699",
      "name": "Merry Hog",
      "slug": "belatra-merry-hog",
      "thumbnailUrl": "https://mediumrare.imgix.net/6cac4ebee83f223c2c4d3068cffc9284e138139205c7be0e02a5b9a78ccffc3c",
      "thumbnailBlurHash": "eZJa..oz0wWCNY[Rj[JRaxf+0je.W[bHt9K%niWEbIjG59V@%2aeng",
      "isBlocked": false,
      "isWidgetEnabled": true,
      "playerCount": 0,
      "groupGames": []
    },
    {
      "id": "ea5a3d1c-96b1-4962-8f7d-22ec5e7e750d",
      "name": "Fortune Craft",
      "slug": "belatra-fortune-craft",
      "thumbnailUrl": "https://mediumrare.imgix.net/94ea66cec9d8ffe4b9d82f7dd4acdb5f8ce5c1f1c9071551b5588c484983605b",
      "thumbnailBlurHash": "eRJsSKR*0zoN$$EHRkXmWr-os@sq-WNat2*Fjbv~WXInMLNG%1s;S0",
      "isBlocked": false,
      "isWidgetEnabled": true,
      "playerCount": 0,
      "groupGames": []
    },
    {
      "id": "dde64e6a-14f0-44df-813e-e0883784a373",
      "name": "Lucky Drink in Egypt",
      "slug": "belatra-lucky-drink-in-egypt",
      "thumbnailUrl": "https://mediumrare.imgix.net/eae59d79c489cc9c94c151fc3f222115e7abcc164a68e61f7c946eb16e7fe9ef",
      "thumbnailBlurHash": "eROKxBWCZibbrX1:jIS%W;t7v3kBV]niXlCmbEZjoLR$Mcf6b^j@X9",
      "isBlocked": false,
      "isWidgetEnabled": true,
      "playerCount": 0,
      "groupGames": []
    },
    {
      "id": "969899a2-3549-4566-bac2-0ed2f1164890",
      "name": "Dracula Riches",
      "slug": "belatra-dracula-riches",
      "thumbnailUrl": "https://mediumrare.imgix.net/2e3abc8f499040a88e5e1330885b8a67be423b8478c25499e74571198a70d15b",
      "thumbnailBlurHash": "eWIrjuWUx|t7Io^yj]?bkCocXWs.$|RjoI-it5RjRiV@4rkDWBazt5",
      "isBlocked": false,
      "isWidgetEnabled": true,
      "playerCount": 0,
      "groupGames": []
    },
    {
      "id": "c61ccc71-95b7-4b5d-a7a4-3640ccae14e3",
      "name": "Carousel",
      "slug": "belatra-carousel",
      "thumbnailUrl": "https://mediumrare.imgix.net/f6eb7aa3f39b52f29999bfb312067c9d7d25f669ea4123361c62dc58c8677af1",
      "thumbnailBlurHash": "ekLDQZxU9PoHWGEsobIwjrog#IR.NNWXo0PmSOR:W=aJMfobt6oboa",
      "isBlocked": false,
      "isWidgetEnabled": true,
      "playerCount": 0,
      "groupGames": []
    },
    {
      "id": "247fdfbe-568d-4097-aaa5-a79c239bd0b4",
      "name": "Lucky Drink",
      "slug": "belatra-lucky-drink",
      "thumbnailUrl": "https://mediumrare.imgix.net/1cac53b4b0c4c66fb27c01fdf81bc73bd5b006d0d31e89f5535efc19fb62c47b",
      "thumbnailBlurHash": "eVPN90tQ$cxGe9tHX7x[WCX9{2W;R.R+S#G[xFMys:adq[nhtRbItQ",
      "isBlocked": false,
      "isWidgetEnabled": true,
      "playerCount": 0,
      "groupGames": []
    },
    {
      "id": "af1e3957-5f29-4d0f-b886-e70f9e09a3cc",
      "name": "The Ghost Walks",
      "slug": "belatra-ghost-walks",
      "thumbnailUrl": "https://mediumrare.imgix.net/32cd1ad58852337beadc67d185a0d3bd813c3e5ea1aa0c6d533a834be1415e0e",
      "thumbnailBlurHash": "eiM7=xWXD+bID+~fWYWCR+RkRtWZt8NGof--fha$ayogN3f6adt7xt",
      "isBlocked": false,
      "isWidgetEnabled": true,
      "playerCount": 0,
      "groupGames": []
    },
    {
      "id": "3d56ac0b-fc69-43e2-8d25-7c647ae414eb",
      "name": "Golden Lantern",
      "slug": "belatra-golden-lantern",
      "thumbnailUrl": "https://mediumrare.imgix.net/4eb1c19cb21ac2cb490605964f7bed625c099a5fc7b43065c7b04f5f4d678b37",
      "thumbnailBlurHash": "ecSW-ZixxHi_tfoXoIo$WBpHxSkUS5brkWu6aeWTocaKq]aeo}ocV{",
      "isBlocked": false,
      "isWidgetEnabled": true,
      "playerCount": 0,
      "groupGames": []
    },
    {
      "id": "5f6ff6d8-47be-41b1-a295-bf3daa8c4911",
      "name": "Icy Fruits",
      "slug": "belatra-icy-fruits",
      "thumbnailUrl": "https://mediumrare.imgix.net/04e376647c722a140eceba816621328c3ce3f6fd8e6854f84a129faff5f0d124",
      "thumbnailBlurHash": "eNI6NuxnT5o$OZ%Sj;-=s=xsKPRj$yjKnh?[baMfaOIV5Ij]wJe.t0",
      "isBlocked": false,
      "isWidgetEnabled": true,
      "playerCount": 0,
      "groupGames": []
    },
    {
      "id": "f0659464-6751-4187-9ada-b4d2f30f448c",
      "name": "Love Magic",
      "slug": "belatra-love-magic",
      "thumbnailUrl": "https://mediumrare.imgix.net/a68715ad243568111adaf313ea539547fb92ab35084486c2fdb81c435f064a0e",
      "thumbnailBlurHash": "e=FH@lR$J6a}bYurR%rva#oLr.Wqoej@WX$%j]SwjuWVOmjbsBa#n+",
      "isBlocked": false,
      "isWidgetEnabled": true,
      "playerCount": 0,
      "groupGames": []
    },
    {
      "id": "cb818885-e668-468a-b988-907020d51845",
      "name": "The Smart Rabbit",
      "slug": "belatra-the-smart-rabbit",
      "thumbnailUrl": "https://mediumrare.imgix.net/a0001c45d413c12121c0fa92b22da8788b1cdcbf38c46798c825c75c192bc1dc",
      "thumbnailBlurHash": "edKAgaXm6n#+OYKjOETejrg419OD$MS#s.cZs.rWnji^IdwIxWa1n#",
      "isBlocked": false,
      "isWidgetEnabled": true,
      "playerCount": 0,
      "groupGames": []
    },
    {
      "id": "2f7ef99b-98c3-49ef-b69a-d97dc1065d13",
      "name": "Elusive Gonzales",
      "slug": "belatra-the-elusive-gonzales",
      "thumbnailUrl": "https://mediumrare.imgix.net/c14e357e82a89f8ca8acd61ea11d64dfda55efcd5796c795312584ea68f60313",
      "thumbnailBlurHash": "elF@A4XTAKWBt7vOXAksWCt7L4WVxaf,WAR.aJnNozRj9_i^xCs:j@",
      "isBlocked": false,
      "isWidgetEnabled": true,
      "playerCount": 0,
      "groupGames": []
    },
    {
      "id": "154dde69-a4de-43ae-af30-d9554f1c17aa",
      "name": "Green Grocery",
      "slug": "belatra-green-grocery",
      "thumbnailUrl": "https://mediumrare.imgix.net/e4150abf9685364bcf44c3f9304de255d28ef3023ce41d3c230234bc6550ac1b",
      "thumbnailBlurHash": "eWP4PVofm8R*#90MoKogWCt7wGf6x[j[X8R@e:v}ofjEq[ayb^ofXS",
      "isBlocked": false,
      "isWidgetEnabled": true,
      "playerCount": 0,
      "groupGames": []
    },
    {
      "id": "b6ab04ae-d6bc-4c2f-8049-ae116397e7fd",
      "name": "Blue Beard",
      "slug": "belatra-blue-beard",
      "thumbnailUrl": "https://mediumrare.imgix.net/606d3e2503eae3028c83d22e9ce954acd1aa53d7cbe05dc70c3be9246ff9cf7a",
      "thumbnailBlurHash": "eVEp?OR61BxYV[Z4RPT2s.xWLMVt%DR+j=sri{w@R*M|5]V{-obIoI",
      "isBlocked": false,
      "isWidgetEnabled": true,
      "playerCount": 0,
      "groupGames": []
    },
    {
      "id": "fb7ede61-7575-4dec-bbd1-021ef1dcc84f",
      "name": "Africa Gold",
      "slug": "belatra-africa-gold",
      "thumbnailUrl": "https://mediumrare.imgix.net/c64c5bf5a76f7863881c96694c26437c513ea2d8ad315cb7373f2a97fc7635b0",
      "thumbnailBlurHash": "eZFZ+|ax22o#jZmja%Ouj]%1ENodr=aes,.SjFemWARi9#afxtW=s.",
      "isBlocked": false,
      "isWidgetEnabled": true,
      "playerCount": 0,
      "groupGames": []
    },
    {
      "id": "fe34a0cc-e960-4a4c-af1d-2057d3156dcd",
      "name": "Princess Of Swamp",
      "slug": "belatra-princess-of-swamp",
      "thumbnailUrl": "https://mediumrare.imgix.net/1b049f3879d45170e249a63303fc4879a0136ffd7bdf7570da73f27cef5d74c4",
      "thumbnailBlurHash": "eYKVX3ow9}a%I]{aoybHn+X97hbcjYsloew1kCRkWVaxAHr?$%Shs,",
      "isBlocked": false,
      "isWidgetEnabled": true,
      "playerCount": 0,
      "groupGames": []
    },
    {
      "id": "eae5efba-ffaa-4b59-93c5-3f8341b3a7d3",
      "name": "Golden Lemon Deluxe",
      "slug": "belatra-golden-lemon-deluxe",
      "thumbnailUrl": "https://mediumrare.imgix.net/c51e6e9316277a3580a25055579e74f3d4f2bc6b130283d10970e80e534d7ffc",
      "thumbnailBlurHash": "ejEqjbs,5YR.S~zmoeNzWCkCGaW=xVjYs9IeWXxAoKaLIon%$~j?Sh",
      "isBlocked": false,
      "isWidgetEnabled": true,
      "playerCount": 0,
      "groupGames": []
    }
  ]
}